ShiyanlouGolangJiaochengHeji20160904/README.md
ShiyanlouGolangJiaochengHeji20160904/__init__.py
ShiyanlouGolangJiaochengHeji20160904/__main__.py
ShiyanlouGolangJiaochengHeji20160904/file.epub
ShiyanlouGolangJiaochengHeji20160904/index.html
ShiyanlouGolangJiaochengHeji20160904/css/__init__.py
ShiyanlouGolangJiaochengHeji20160904/css/annotations.css
ShiyanlouGolangJiaochengHeji20160904/css/main.css
ShiyanlouGolangJiaochengHeji20160904/css/normalize.css
ShiyanlouGolangJiaochengHeji20160904/css/popup.css
ShiyanlouGolangJiaochengHeji20160904/font/__init__.py
ShiyanlouGolangJiaochengHeji20160904/font/fontello.eot
ShiyanlouGolangJiaochengHeji20160904/font/fontello.svg
ShiyanlouGolangJiaochengHeji20160904/font/fontello.ttf
ShiyanlouGolangJiaochengHeji20160904/font/fontello.woff
ShiyanlouGolangJiaochengHeji20160904/img/__init__.py
ShiyanlouGolangJiaochengHeji20160904/img/annotator-glyph-sprite.png
ShiyanlouGolangJiaochengHeji20160904/img/annotator-icon-sprite.png
ShiyanlouGolangJiaochengHeji20160904/img/apple-touch-icon.png
ShiyanlouGolangJiaochengHeji20160904/img/cancelfullscreen.png
ShiyanlouGolangJiaochengHeji20160904/img/close.png
ShiyanlouGolangJiaochengHeji20160904/img/fullscreen.png
ShiyanlouGolangJiaochengHeji20160904/img/loader.gif
ShiyanlouGolangJiaochengHeji20160904/img/menu-icon.png
ShiyanlouGolangJiaochengHeji20160904/img/save.png
ShiyanlouGolangJiaochengHeji20160904/img/saved.png
ShiyanlouGolangJiaochengHeji20160904/img/settings-s.png
ShiyanlouGolangJiaochengHeji20160904/img/settings.png
ShiyanlouGolangJiaochengHeji20160904/img/star.png
ShiyanlouGolangJiaochengHeji20160904/js/__init__.py
ShiyanlouGolangJiaochengHeji20160904/js/epub.js
ShiyanlouGolangJiaochengHeji20160904/js/epub.min.js
ShiyanlouGolangJiaochengHeji20160904/js/epub.min.map
ShiyanlouGolangJiaochengHeji20160904/js/hooks.min.js
ShiyanlouGolangJiaochengHeji20160904/js/hooks.min.map
ShiyanlouGolangJiaochengHeji20160904/js/reader.js
ShiyanlouGolangJiaochengHeji20160904/js/reader.js.map
shiyanlou_golang_jiaocheng_heji_20160904-2024.3.1.0.dist-info/METADATA
shiyanlou_golang_jiaocheng_heji_20160904-2024.3.1.0.dist-info/WHEEL
shiyanlou_golang_jiaocheng_heji_20160904-2024.3.1.0.dist-info/entry_points.txt
shiyanlou_golang_jiaocheng_heji_20160904-2024.3.1.0.dist-info/top_level.txt
shiyanlou_golang_jiaocheng_heji_20160904-2024.3.1.0.dist-info/RECORD
